ELFit/LineFitGUI.py
ELFit/__init__.py
ELFit/line_analysis.py
ELFit-0.6.dist-info/LICENSE
ELFit-0.6.dist-info/METADATA
ELFit-0.6.dist-info/WHEEL
ELFit-0.6.dist-info/top_level.txt
ELFit-0.6.dist-info/RECORD
